pychub_hatch_plugin/__init__.py
pychub_hatch_plugin/hooks.py
pychub_hatch_plugin/plugin.py
pychub_hatch_plugin-1.0.4.dist-info/METADATA
pychub_hatch_plugin-1.0.4.dist-info/WHEEL
pychub_hatch_plugin-1.0.4.dist-info/entry_points.txt
pychub_hatch_plugin-1.0.4.dist-info/RECORD
